certbot_dns_active24/__init__.py
certbot_dns_active24/dns_active24.py
certbot_dns_active24-2.0.1.dist-info/licenses/LICENSE.txt
certbot_dns_active24-2.0.1.dist-info/METADATA
certbot_dns_active24-2.0.1.dist-info/WHEEL
certbot_dns_active24-2.0.1.dist-info/entry_points.txt
certbot_dns_active24-2.0.1.dist-info/top_level.txt
certbot_dns_active24-2.0.1.dist-info/RECORD
