Metadata-Version: 2.4
Name: certbot-dns-active24
Version: 2.0.1
Summary: Active24 DNS Authenticator plugin for Certbot
Author-email: Dan Kadera <me@subsonic.cz>
License: MIT
Project-URL: Homepage, https://github.com/jahudka/certbot-dns-active24
Project-URL: Repository, https://github.com/jahudka/certbot-dns-active24.git
Project-URL: Bug Tracker, https://github.com/jahudka/certbot-dns-active24/issues
Keywords: certbot,letsencrypt,dns-01,plugin,authenticator
Classifier: Development Status :: 3 - Alpha
Classifier: Environment :: Plugins
Classifier: Intended Audience :: System Administrators
Classifier: License :: OSI Approved :: Apache Software License
Classifier: Operating System :: POSIX :: Linux
Classifier: Programming Language :: Python
Classifier: Programming Language :: Python :: 3.8
Classifier: Programming Language :: Python :: 3.9
Classifier: Programming Language :: Python :: 3.10
Classifier: Programming Language :: Python :: 3.11
Classifier: Topic :: Internet :: WWW/HTTP
Classifier: Topic :: Security
Classifier: Topic :: System :: Installation/Setup
Classifier: Topic :: System :: Networking
Classifier: Topic :: System :: Systems Administration
Classifier: Topic :: Utilities
Requires-Python: >=3.8
License-File: LICENSE.txt
Requires-Dist: acme>=0.29.0
Requires-Dist: certbot>=0.34.0
Requires-Dist: dnspython
Requires-Dist: mock
Requires-Dist: requests
Requires-Dist: setuptools
Requires-Dist: requests-mock
Requires-Dist: zope.interface
Dynamic: license-file
